<annotations><filename>IMG_4004-color1-f1.jpg</filename><folder>images</folder><size><width>480</width><height>640</height><depth>3</depth></size><object><name>DBM</name><pose>Unspecified</pose><truncated>0</truncated><difficult>0</difficult><bndbox><xmin>255</xmin><ymin>143</ymin><xmax>277</xmax><ymax>175</ymax></bndbox></object><object><name>DBM</name><pose>Unspecified</pose><truncated>0</truncated><difficult>0</difficult><bndbox><xmin>351</xmin><ymin>365</ymin><xmax>380</xmax><ymax>384</ymax></bndbox></object><object><name>DBM</name><pose>Unspecified</pose><truncated>0</truncated><difficult>0</difficult><bndbox><xmin>184</xmin><ymin>521</ymin><xmax>202</xmax><ymax>538</ymax></bndbox></object></annotations>